binaryCounterSaturatedwReset/binaryCounterSaturatedwReset.v
//------------------------------------------------------------------
//-- Hello world example for the iCE40-HX8K board
//-- 8 bit binary counter
//------------------------------------------------------------------


module binaryCounter #(parameter MAX_COUNT = 100)(
            output reg [7:0] leds = 0,
            input clk,
            input rst);

//max is 8 bits which is 255
localparam maxCountLED = 8'hFF;

reg [31:0] count = 0;
always @(posedge clk) begin
    if (leds !=  maxCountLED) begin
        count = count + 1;
        if (count == MAX_COUNT) begin
            leds = leds + 1;
            count = 0;
        end
    end
end

always @(negedge rst) begin
    count  = 0;
    leds = 0;
end

endmodule

binaryCounterSaturatedwReset/binaryCounterSaturatedwReset_tb.v
//------------------------------------------------------------------
//-- Hello world example for the iCE40-HX8K board
//-- 8 bit binary counter
//------------------------------------------------------------------

`timescale 1s/100ns

module binaryCounterSaturatedwReset_tb ();

    //leds outputs
    wire [7:0] leds;

    reg clk = 0;
    reg rst_btn = 1;

    localparam DURATION = 8; // this is 5 seconds
    
    always begin
        #0.0001 //that's 1s/(10kHz)
        clk = ~clk;
    end

    //leds make the saturated binary counter
    binaryCounter #(.MAX_COUNT(100)) uut  (
        .leds(leds),
        .rst(rst_btn),
        .clk(clk)
    );

    initial begin
        #1 //wait a sec
        rst_btn = 0;
        #2 //wait 5 seconds
        rst_btn = 1;
        #4 //wait 4 seconds
        rst_btn = 0;
    end

    //run the simulation
    initial begin
        $dumpfile("binaryCounterSaturatedwReset_tb.vcd");
        $dumpvars(0, binaryCounterSaturatedwReset_tb); //the zero means we wanna see all the variables no matter the depth

        #(DURATION)

        $display("Finished!");
        $finish;
    end
endmodule

binaryCounterSaturatedwReset/binaryCounterSaturatedwReset_tb.vcd
$date
	Thu Oct 20 16:51:13 2022
$end
$version
	Icarus Verilog
$end
$timescale
	1ps
$end
$scope module binaryCounterSaturatedwReset_tb $end
$var wire 8 ! leds [7:0] $end
$var reg 1 " clk $end
$var reg 1 # rst_btn $end
$scope module uut $end
$var wire 1 " clk $end
$var wire 1 # rst $end
$var reg 32 $ count [31:0] $end
$var reg 8 % leds [7:0] $end
$upscope $end
$upscope $end
$enddefinitions $end
#0
$dumpvars
b0 %
b0 $
1#
0"
b0 !
$end
#100000000
b1 $
1"
#200000000
0"
#300000000
b10 $
1"
#400000000
0"
#500000000
b11 $
1"
#600000000
0"
#700000000
b100 $
1"
#800000000
0"
#900000000
b101 $
1"
#1000000000
0"
#1100000000
b110 $
1"
#1200000000
0"
#1300000000
b111 $
1"
#1400000000
0"
#1500000000
b1000 $
1"
#1600000000
0"
#1700000000
b1001 $
1"
#1800000000
0"
#1900000000
b1010 $
1"
#2000000000
0"
#2100000000
b1011 $
1"
#2200000000
0"
#2300000000
b1100 $
1"
#2400000000
0"
#2500000000
b1101 $
1"
#2600000000
0"
#2700000000
b1110 $
1"
#2800000000
0"
#2900000000
b1111 $
1"
#3000000000
0"
#3100000000
b10000 $
1"
#3200000000
0"
#3300000000
b10001 $
1"
#3400000000
0"
#3500000000
b10010 $
1"
#3600000000
0"
#3700000000
b10011 $
1"
#3800000000
0"
#3900000000
b10100 $
1"
#4000000000
0"
#4100000000
b10101 $
1"
#4200000000
0"
#4300000000
b10110 $
1"
#4400000000
0"
#4500000000
b10111 $
1"
#4600000000
0"
#4700000000
b11000 $
1"
#4800000000
0"
#4900000000
b11001 $
1"
#5000000000
0"
#5100000000
b11010 $
1"
#5200000000
0"
#5300000000
b11011 $
1"
#5400000000
0"
#5500000000
b11100 $
1"
#5600000000
0"
#5700000000
b11101 $
1"
#5800000000
0"
#5900000000
b11110 $
1"
#6000000000
0"
#6100000000
b11111 $
1"
#6200000000
0"
#6300000000
b100000 $
1"
#6400000000
0"
#6500000000
b100001 $
1"
#6600000000
0"
#6700000000
b100010 $
1"
#6800000000
0"
#6900000000
b100011 $
1"
#7000000000
0"
#7100000000
b100100 $
1"
#7200000000
0"
#7300000000
b100101 $
1"
#7400000000
0"
#7500000000
b100110 $
1"
#7600000000
0"
#7700000000
b100111 $
1"
#7800000000
0"
#7900000000
b101000 $
1"
#8000000000
0"
#8100000000
b101001 $
1"
#8200000000
0"
#8300000000
b101010 $
1"
#8400000000
0"
#8500000000
b101011 $
1"
#8600000000
0"
#8700000000
b101100 $
1"
#8800000000
0"
#8900000000
b101101 $
1"
#9000000000
0"
#9100000000
b101110 $
1"
#9200000000
0"
#9300000000
b101111 $
1"
#9400000000
0"
#9500000000
b110000 $
1"
#9600000000
0"
#9700000000
b110001 $
1"
#9800000000
0"
#9900000000
b110010 $
1"
#10000000000
0"
#10100000000
b110011 $
1"
#10200000000
0"
#10300000000
b110100 $
1"
#10400000000
0"
#10500000000
b110101 $
1"
#10600000000
0"
#10700000000
b110110 $
1"
#10800000000
0"
#10900000000
b110111 $
1"
#11000000000
0"
#11100000000
b111000 $
1"
#11200000000
0"
#11300000000
b111001 $
1"
#11400000000
0"
#11500000000
b111010 $
1"
#11600000000
0"
#11700000000
b111011 $
1"
#11800000000
0"
#11900000000
b111100 $
1"
#12000000000
0"
#12100000000
b111101 $
1"
#12200000000
0"
#12300000000
b111110 $
1"
#12400000000
0"
#12500000000
b111111 $
1"
#12600000000
0"
#12700000000
b1000000 $
1"
#12800000000
0"
#12900000000
b1000001 $
1"
#13000000000
0"
#13100000000
b1000010 $
1"
#13200000000
0"
#13300000000
b1000011 $
1"
#13400000000
0"
#13500000000
b1000100 $
1"
#13600000000
0"
#13700000000
b1000101 $
1"
#13800000000
0"
#13900000000
b1000110 $
1"
#14000000000
0"
#14100000000
b1000111 $
1"
#14200000000
0"
#14300000000
b1001000 $
1"
#14400000000
0"
#14500000000
b1001001 $
1"
#14600000000
0"
#14700000000
b1001010 $
1"
#14800000000
0"
#14900000000
b1001011 $
1"
#15000000000
0"
#15100000000
b1001100 $
1"
#15200000000
0"
#15300000000
b1001101 $
1"
#15400000000
0"
#15500000000
b1001110 $
1"
#15600000000
0"
#15700000000
b1001111 $
1"
#15800000000
0"
#15900000000
b1010000 $
1"
#16000000000
0"
#16100000000
b1010001 $
1"
#16200000000
0"
#16300000000
b1010010 $
1"
#16400000000
0"
#16500000000
b1010011 $
1"
#16600000000
0"
#16700000000
b1010100 $
1"
#16800000000
0"
#16900000000
b1010101 $
1"
#17000000000
0"
#17100000000
b1010110 $
1"
#17200000000
0"
#17300000000
b1010111 $
1"
#17400000000
0"
#17500000000
b1011000 $
1"
#17600000000
0"
#17700000000
b1011001 $
1"
#17800000000
0"
#17900000000
b1011010 $
1"
#18000000000
0"
#18100000000
b1011011 $
1"
#18200000000
0"
#18300000000
b1011100 $
1"
#18400000000
0"
#18500000000
b1011101 $
1"
#18600000000
0"
#18700000000
b1011110 $
1"
#18800000000
0"
#18900000000
b1011111 $
1"
#19000000000
0"
#19100000000
b1100000 $
1"
#19200000000
0"
#19300000000
b1100001 $
1"
#19400000000
0"
#19500000000
b1100010 $
1"
#19600000000
0"
#19700000000
b1100011 $
1"
#19800000000
0"
#19900000000
b1 !
b1 %
b0 $
1"
#20000000000
0"
#20100000000
b1 $
1"
#20200000000
0"
#20300000000
b10 $
1"
#20400000000
0"
#20500000000
b11 $
1"
#20600000000
0"
#20700000000
b100 $
1"
#20800000000
0"
#20900000000
b101 $
1"
#21000000000
0"
#21100000000
b110 $
1"
#21200000000
0"
#21300000000
b111 $
1"
#21400000000
0"
#21500000000
b1000 $
1"
#21600000000
0"
#21700000000
b1001 $
1"
#21800000000
0"
#21900000000
b1010 $
1"
#22000000000
0"
#22100000000
b1011 $
1"
#22200000000
0"
#22300000000
b1100 $
1"
#22400000000
0"
#22500000000
b1101 $
1"
#22600000000
0"
#22700000000
b1110 $
1"
#22800000000
0"
#22900000000
b1111 $
1"
#23000000000
0"
#23100000000
b10000 $
1"
#23200000000
0"
#23300000000
b10001 $
1"
#23400000000
0"
#23500000000
b10010 $
1"
#23600000000
0"
#23700000000
b10011 $
1"
#23800000000
0"
#23900000000
b10100 $
1"
#24000000000
0"
#24100000000
b10101 $
1"
#24200000000
0"
#24300000000
b10110 $
1"
#24400000000
0"
#24500000000
b10111 $
1"
#24600000000
0"
#24700000000
b11000 $
1"
#24800000000
0"
#24900000000
b11001 $
1"
#25000000000
0"
#25100000000
b11010 $
1"
#25200000000
0"
#25300000000
b11011 $
1"
#25400000000
0"
#25500000000
b11100 $
1"
#25600000000
0"
#25700000000
b11101 $
1"
#25800000000
0"
#25900000000
b11110 $
1"
#26000000000
0"
#26100000000
b11111 $
1"
#26200000000
0"
#26300000000
b100000 $
1"
#26400000000
0"
#26500000000
b100001 $
1"
#26600000000
0"
#26700000000
b100010 $
1"
#26800000000
0"
#26900000000
b100011 $
1"
#27000000000
0"
#27100000000
b100100 $
1"
#27200000000
0"
#27300000000
b100101 $
1"
#27400000000
0"
#27500000000
b100110 $
1"
#27600000000
0"
#27700000000
b100111 $
1"
#27800000000
0"
#27900000000
b101000 $
1"
#28000000000
0"
#28100000000
b101001 $
1"
#28200000000
0"
#28300000000
b101010 $
1"
#28400000000
0"
#28500000000
b101011 $
1"
#28600000000
0"
#28700000000
b101100 $
1"
#28800000000
0"
#28900000000
b101101 $
1"
#29000000000
0"
#29100000000
b101110 $
1"
#29200000000
0"
#29300000000
b101111 $
1"
#29400000000
0"
#29500000000
b110000 $
1"
#29600000000
0"
#29700000000
b110001 $
1"
#29800000000
0"
#29900000000
b110010 $
1"
#30000000000
0"
#30100000000
b110011 $
1"
#30200000000
0"
#30300000000
b110100 $
1"
#30400000000
0"
#30500000000
b110101 $
1"
#30600000000
0"
#30700000000
b110110 $
1"
#30800000000
0"
#30900000000
b110111 $
1"
#31000000000
0"
#31100000000
b111000 $
1"
#31200000000
0"
#31300000000
b111001 $
1"
#31400000000
0"
#31500000000
b111010 $
1"
#31600000000
0"
#31700000000
b111011 $
1"
#31800000000
0"
#31900000000
b111100 $
1"
#32000000000
0"
#32100000000
b111101 $
1"
#32200000000
0"
#32300000000
b111110 $
1"
#32400000000
0"
#32500000000
b111111 $
1"
#32600000000
0"
#32700000000
b1000000 $
1"
#32800000000
0"
#32900000000
b1000001 $
1"
#33000000000
0"
#33100000000
b1000010 $
1"
#33200000000
0"
#33300000000
b1000011 $
1"
#33400000000
0"
#33500000000
b1000100 $
1"
#33600000000
0"
#33700000000
b1000101 $
1"
#33800000000
0"
#33900000000
b1000110 $
1"
#34000000000
0"
#34100000000
b1000111 $
1"
#34200000000
0"
#34300000000
b1001000 $
1"
#34400000000
0"
#34500000000
b1001001 $
1"
#34600000000
0"
#34700000000
b1001010 $
1"
#34800000000
0"
#34900000000
b1001011 $
1"
#35000000000
0"
#35100000000
b1001100 $
1"
#35200000000
0"
#35300000000
b1001101 $
1"
#35400000000
0"
#35500000000
b1001110 $
1"
#35600000000
0"
#35700000000
b1001111 $
1"
#35800000000
0"
#35900000000
b1010000 $
1"
#36000000000
0"
#36100000000
b1010001 $
1"
#36200000000
0"
#36300000000
b1010010 $
1"
#36400000000
0"
#36500000000
b1010011 $
1"
#36600000000
0"
#36700000000
b1010100 $
1"
#36800000000
0"
#36900000000
b1010101 $
1"
#37000000000
0"
#37100000000
b1010110 $
1"
#37200000000
0"
#37300000000
b1010111 $
1"
#37400000000
0"
#37500000000
b1011000 $
1"
#37600000000
0"
#37700000000
b1011001 $
1"
#37800000000
0"
#37900000000
b1011010 $
1"
#38000000000
0"
#38100000000
b1011011 $
1"
#38200000000
0"
#38300000000
b1011100 $
1"
#38400000000
0"
#38500000000
b1011101 $
1"
#38600000000
0"
#38700000000
b1011110 $
1"
#38800000000
0"
#38900000000
b1011111 $
1"
#39000000000
0"
#39100000000
b1100000 $
1"
#39200000000
0"
#39300000000
b1100001 $
1"
#39400000000
0"
#39500000000
b1100010 $
1"
#39600000000
0"
#39700000000
b1100011 $
1"
#39800000000
0"
#39900000000
b10 !
b10 %
b0 $
1"
#40000000000
0"
#40100000000
b1 $
1"
#40200000000
0"
#40300000000
b10 $
1"
#40400000000
0"
#40500000000
b11 $
1"
#40600000000
0"
#40700000000
b100 $
1"
#40800000000
0"
#40900000000
b101 $
1"
#41000000000
0"
#41100000000
b110 $
1"
#41200000000
0"
#41300000000
b111 $
1"
#41400000000
0"
#41500000000
b1000 $
1"
#41600000000
0"
#41700000000
b1001 $
1"
#41800000000
0"
#41900000000
b1010 $
1"
#42000000000
0"
#42100000000
b1011 $
1"
#42200000000
0"
#42300000000
b1100 $
1"
#42400000000
0"
#42500000000
b1101 $
1"
#42600000000
0"
#42700000000
b1110 $
1"
#42800000000
0"
#42900000000
b1111 $
1"
#43000000000
0"
#43100000000
b10000 $
1"
#43200000000
0"
#43300000000
b10001 $
1"
#43400000000
0"
#43500000000
b10010 $
1"
#43600000000
0"
#43700000000
b10011 $
1"
#43800000000
0"
#43900000000
b10100 $
1"
#44000000000
0"
#44100000000
b10101 $
1"
#44200000000
0"
#44300000000
b10110 $
1"
#44400000000
0"
#44500000000
b10111 $
1"
#44600000000
0"
#44700000000
b11000 $
1"
#44800000000
0"
#44900000000
b11001 $
1"
#45000000000
0"
#45100000000
b11010 $
1"
#45200000000
0"
#45300000000
b11011 $
1"
#45400000000
0"
#45500000000
b11100 $
1"
#45600000000
0"
#45700000000
b11101 $
1"
#45800000000
0"
#45900000000
b11110 $
1"
#46000000000
0"
#46100000000
b11111 $
1"
#46200000000
0"
#46300000000
b100000 $
1"
#46400000000
0"
#46500000000
b100001 $
1"
#46600000000
0"
#46700000000
b100010 $
1"
#46800000000
0"
#46900000000
b100011 $
1"
#47000000000
0"
#47100000000
b100100 $
1"
#47200000000
0"
#47300000000
b100101 $
1"
#47400000000
0"
#47500000000
b100110 $
1"
#47600000000
0"
#47700000000
b100111 $
1"
#47800000000
0"
#47900000000
b101000 $
1"
#48000000000
0"
#48100000000
b101001 $
1"
#48200000000
0"
#48300000000
b101010 $
1"
#48400000000
0"
#48500000000
b101011 $
1"
#48600000000
0"
#48700000000
b101100 $
1"
#48800000000
0"
#48900000000
b101101 $
1"
#49000000000
0"
#49100000000
b101110 $
1"
#49200000000
0"
#49300000000
b101111 $
1"
#49400000000
0"
#49500000000
b110000 $
1"
#49600000000
0"
#49700000000
b110001 $
1"
#49800000000
0"
#49900000000
b110010 $
1"
#50000000000
0"
#50100000000
b110011 $
1"
#50200000000
0"
#50300000000
b110100 $
1"
#50400000000
0"
#50500000000
b110101 $
1"
#50600000000
0"
#50700000000
b110110 $
1"
#50800000000
0"
#50900000000
b110111 $
1"
#51000000000
0"
#51100000000
b111000 $
1"
#51200000000
0"
#51300000000
b111001 $
1"
#51400000000
0"
#51500000000
b111010 $
1"
#51600000000
0"
#51700000000
b111011 $
1"
#51800000000
0"
#51900000000
b111100 $
1"
#52000000000
0"
#52100000000
b111101 $
1"
#52200000000
0"
#52300000000
b111110 $
1"
#52400000000
0"
#52500000000
b111111 $
1"
#52600000000
0"
#52700000000
b1000000 $
1"
#52800000000
0"
#52900000000
b1000001 $
1"
#53000000000
0"
#53100000000
b1000010 $
1"
#53200000000
0"
#53300000000
b1000011 $
1"
#53400000000
0"
#53500000000
b1000100 $
1"
#53600000000
0"
#53700000000
b1000101 $
1"
#53800000000
0"
#53900000000
b1000110 $
1"
#54000000000
0"
#54100000000
b1000111 $
1"
#54200000000
0"
#54300000000
b1001000 $
1"
#54400000000
0"
#54500000000
b1001001 $
1"
#54600000000
0"
#54700000000
b1001010 $
1"
#54800000000
0"
#54900000000
b1001011 $
1"
#55000000000
0"
#55100000000
b1001100 $
1"
#55200000000
0"
#55300000000
b1001101 $
1"
#55400000000
0"
#55500000000
b1001110 $
1"
#55600000000
0"
#55700000000
b1001111 $
1"
#55800000000
0"
#55900000000
b1010000 $
1"
#56000000000
0"
#56100000000
b1010001 $
1"
#56200000000
0"
#56300000000
b1010010 $
1"
#56400000000
0"
#56500000000
b1010011 $
1"
#56600000000
0"
#56700000000
b1010100 $
1"
#56800000000
0"
#56900000000
b1010101 $
1"
#57000000000
0"
#57100000000
b1010110 $
1"
#57200000000
0"
#57300000000
b1010111 $
1"
#57400000000
0"
#57500000000
b1011000 $
1"
#57600000000
0"
#57700000000
b1011001 $
1"
#57800000000
0"
#57900000000
b1011010 $
1"
#58000000000
0"
#58100000000
b1011011 $
1"
#58200000000
0"
#58300000000
b1011100 $
1"
#58400000000
0"
#58500000000
b1011101 $
1"
#58600000000
0"
#58700000000
b1011110 $
1"
#58800000000
0"
#58900000000
b1011111 $
1"
#59000000000
0"
#59100000000
b1100000 $
1"
#59200000000
0"
#59300000000
b1100001 $
1"
#59400000000
0"
#59500000000
b1100010 $
1"
#59600000000
0"
#59700000000
b1100011 $
1"
#59800000000
0"
#59900000000
b11 !
b11 %
b0 $
1"
#60000000000
0"
#60100000000
b1 $
1"
#60200000000
0"
#60300000000
b10 $
1"
#60400000000
0"
#60500000000
b11 $
1"
#60600000000
0"
#60700000000
b100 $
1"
#60800000000
0"
#60900000000
b101 $
1"
#61000000000
0"
#61100000000
b110 $
1"
#61200000000
0"
#61300000000
b111 $
1"
#61400000000
0"
#61500000000
b1000 $
1"
#61600000000
0"
#61700000000
b1001 $
1"
#61800000000
0"
#61900000000
b1010 $
1"
#62000000000
0"
#62100000000
b1011 $
1"
#62200000000
0"
#62300000000
b1100 $
1"
#62400000000
0"
#62500000000
b1101 $
1"
#62600000000
0"
#62700000000
b1110 $
1"
#62800000000
0"
#62900000000
b1111 $
1"
#63000000000
0"
#63100000000
b10000 $
1"
#63200000000
0"
#63300000000
b10001 $
1"
#63400000000
0"
#63500000000
b10010 $
1"
#63600000000
0"
#63700000000
b10011 $
1"
#63800000000
0"
#63900000000
b10100 $
1"
#64000000000
0"
#64100000000
b10101 $
1"
#64200000000
0"
#64300000000
b10110 $
1"
#64400000000
0"
#64500000000
b10111 $
1"
#64600000000
0"
#64700000000
b11000 $
1"
#64800000000
0"
#64900000000
b11001 $
1"
#65000000000
0"
#65100000000
b11010 $
1"
#65200000000
0"
#65300000000
b11011 $
1"
#65400000000
0"
#65500000000
b11100 $
1"
#65600000000
0"
#65700000000
b11101 $
1"
#65800000000
0"
#65900000000
b11110 $
1"
#66000000000
0"
#66100000000
b11111 $
1"
#66200000000
0"
#66300000000
b100000 $
1"
#66400000000
0"
#66500000000
b100001 $
1"
#66600000000
0"
#66700000000
b100010 $
1"
#66800000000
0"
#66900000000
b100011 $
1"
#67000000000
0"
#67100000000
b100100 $
1"
#67200000000
0"
#67300000000
b100101 $
1"
#67400000000
0"
#67500000000
b100110 $
1"
#67600000000
0"
#67700000000
b100111 $
1"
#67800000000
0"
#67900000000
b101000 $
1"
#68000000000
0"
#68100000000
b101001 $
1"
#68200000000
0"
#68300000000
b101010 $
1"
#68400000000
0"
#68500000000
b101011 $
1"
#68600000000
0"
#68700000000
b101100 $
1"
#68800000000
0"
#68900000000
b101101 $
1"
#69000000000
0"
#69100000000
b101110 $
1"
#69200000000
0"
#69300000000
b101111 $
1"
#69400000000
0"
#69500000000
b110000 $
1"
#69600000000
0"
#69700000000
b110001 $
1"
#69800000000
0"
#69900000000
b110010 $
1"
#70000000000
0"
#70100000000
b110011 $
1"
#70200000000
0"
#70300000000
b110100 $
1"
#70400000000
0"
#70500000000
b110101 $
1"
#70600000000
0"
#70700000000
b110110 $
1"
#70800000000
0"
#70900000000
b110111 $
1"
#71000000000
0"
#71100000000
b111000 $
1"
#71200000000
0"
#71300000000
b111001 $
1"
#71400000000
0"
#71500000000
b111010 $
1"
#71600000000
0"
#71700000000
b111011 $
1"
#71800000000
0"
#71900000000
b111100 $
1"
#72000000000
0"
#72100000000
b111101 $
1"
#72200000000
0"
#72300000000
b111110 $
1"
#72400000000
0"
#72500000000
b111111 $
1"
#72600000000
0"
#72700000000
b1000000 $
1"
#72800000000
0"
#72900000000
b1000001 $
1"
#73000000000
0"
#73100000000
b1000010 $
1"
#73200000000
0"
#73300000000
b1000011 $
1"
#73400000000
0"
#73500000000
b1000100 $
1"
#73600000000
0"
#73700000000
b1000101 $
1"
#73800000000
0"
#73900000000
b1000110 $
1"
#74000000000
0"
#74100000000
b1000111 $
1"
#74200000000
0"
#74300000000
b1001000 $
1"
#74400000000
0"
#74500000000
b1001001 $
1"
#74600000000
0"
#74700000000
b1001010 $
1"
#74800000000
0"
#74900000000
b1001011 $
1"
#75000000000
0"
#75100000000
b1001100 $
1"
#75200000000
0"
#75300000000
b1001101 $
1"
#75400000000
0"
#75500000000
b1001110 $
1"
#75600000000
0"
#75700000000
b1001111 $
1"
#75800000000
0"
#75900000000
b1010000 $
1"
#76000000000
0"
#76100000000
b1010001 $
1"
#76200000000
0"
#76300000000
b1010010 $
1"
#76400000000
0"
#76500000000
b1010011 $
1"
#76600000000
0"
#76700000000
b1010100 $
1"
#76800000000
0"
#76900000000
b1010101 $
1"
#77000000000
0"
#77100000000
b1010110 $
1"
#77200000000
0"
#77300000000
b1010111 $
1"
#77400000000
0"
#77500000000
b1011000 $
1"
#77600000000
0"
#77700000000
b1011001 $
1"
#77800000000
0"
#77900000000
b1011010 $
1"
#78000000000
0"
#78100000000
b1011011 $
1"
#78200000000
0"
#78300000000
b1011100 $
1"
#78400000000
0"
#78500000000
b1011101 $
1"
#78600000000
0"
#78700000000
b1011110 $
1"
#78800000000
0"
#78900000000
b1011111 $
1"
#79000000000
0"
#79100000000
b1100000 $
1"
#79200000000
0"
#79300000000
b1100001 $
1"
#79400000000
0"
#79500000000
b1100010 $
1"
#79600000000
0"
#79700000000
b1100011 $
1"
#79800000000
0"
#79900000000
b100 !
b100 %
b0 $
1"
#80000000000
0"
#80100000000
b1 $
1"
#80200000000
0"
#80300000000
b10 $
1"
#80400000000
0"
#80500000000
b11 $
1"
#80600000000
0"
#80700000000
b100 $
1"
#80800000000
0"
#80900000000
b101 $
1"
#81000000000
0"
#81100000000
b110 $
1"
#81200000000
0"
#81300000000
b111 $
1"
#81400000000
0"
#81500000000
b1000 $
1"
#81600000000
0"
#81700000000
b1001 $
1"
#81800000000
0"
#81900000000
b1010 $
1"
#82000000000
0"
#82100000000
b1011 $
1"
#82200000000
0"
#82300000000
b1100 $
1"
#82400000000
0"
#82500000000
b1101 $
1"
#82600000000
0"
#82700000000
b1110 $
1"
#82800000000
0"
#82900000000
b1111 $
1"
#83000000000
0"
#83100000000
b10000 $
1"
#83200000000
0"
#83300000000
b10001 $
1"
#83400000000
0"
#83500000000
b10010 $
1"
#83600000000
0"
#83700000000
b10011 $
1"
#83800000000
0"
#83900000000
b10100 $
1"
#84000000000
0"
#84100000000
b10101 $
1"
#84200000000
0"
#84300000000
b10110 $
1"
#84400000000
0"
#84500000000
b10111 $
1"
#84600000000
0"
#84700000000
b11000 $
1"
#84800000000
0"
#84900000000
b11001 $
1"
#85000000000
0"
#85100000000
b11010 $
1"
#85200000000
0"
#85300000000
b11011 $
1"
#85400000000
0"
#85500000000
b11100 $
1"
#85600000000
0"
#85700000000
b11101 $
1"
#85800000000
0"
#85900000000
b11110 $
1"
#86000000000
0"
#86100000000
b11111 $
1"
#86200000000
0"
#86300000000
b100000 $
1"
#86400000000
0"
#86500000000
b100001 $
1"
#86600000000
0"
#86700000000
b100010 $
1"
#86800000000
0"
#86900000000
b100011 $
1"
#87000000000
0"
#87100000000
b100100 $
1"
#87200000000
0"
#87300000000
b100101 $
1"
#87400000000
0"
#87500000000
b100110 $
1"
#87600000000
0"
#87700000000
b100111 $
1"
#87800000000
0"
#87900000000
b101000 $
1"
#88000000000
0"
#88100000000
b101001 $
1"
#88200000000
0"
#88300000000
b101010 $
1"
#88400000000
0"
#88500000000
b101011 $
1"
#88600000000
0"
#88700000000
b101100 $
1"
#88800000000
0"
#88900000000
b101101 $
1"
#89000000000
0"
#89100000000
b101110 $
1"
#89200000000
0"
#89300000000
b101111 $
1"
#89400000000
0"
#89500000000
b110000 $
1"
#89600000000
0"
#89700000000
b110001 $
1"
#89800000000
0"
#89900000000
b110010 $
1"
#90000000000
0"
#90100000000
b110011 $
1"
#90200000000
0"
#90300000000
b110100 $
1"
#90400000000
0"
#90500000000
b110101 $
1"
#90600000000
0"
#90700000000
b110110 $
1"
#90800000000
0"
#90900000000
b110111 $
1"
#91000000000
0"
#91100000000
b111000 $
1"
#91200000000
0"
#91300000000
b111001 $
1"
#91400000000
0"
#91500000000
b111010 $
1"
#91600000000
0"
#91700000000
b111011 $
1"
#91800000000
0"
#91900000000
b111100 $
1"
#92000000000
0"
#92100000000
b111101 $
1"
#92200000000
0"
#92300000000
b111110 $
1"
#92400000000
0"
#92500000000
b111111 $
1"
#92600000000
0"
#92700000000
b1000000 $
1"
#92800000000
0"
#92900000000
b1000001 $
1"
#93000000000
0"
#93100000000
b1000010 $
1"
#93200000000
0"
#93300000000
b1000011 $
1"
#93400000000
0"
#93500000000
b1000100 $
1"
#93600000000
0"
#93700000000
b1000101 $
1"
#93800000000
0"
#93900000000
b1000110 $
1"
#94000000000
0"
#94100000000
b1000111 $
1"
#94200000000
0"
#94300000000
b1001000 $
1"
#94400000000
0"
#94500000000
b1001001 $
1"
#94600000000
0"
#94700000000
b1001010 $
1"
#94800000000
0"
#94900000000
b1001011 $
1"
#95000000000
0"
#95100000000
b1001100 $
1"
#95200000000
0"
#95300000000
b1001101 $
1"
#95400000000
0"
#95500000000
b1001110 $
1"
#95600000000
0"
#95700000000
b1001111 $
1"
#95800000000
0"
#95900000000
b1010000 $
1"
#96000000000
0"
#96100000000
b1010001 $
1"
#96200000000
0"
#96300000000
b1010010 $
1"
#96400000000
0"
#96500000000
b1010011 $
1"
#96600000000
0"
#96700000000
b1010100 $
1"
#96800000000
0"
#96900000000
b1010101 $
1"
#97000000000
0"
#97100000000
b1010110 $
1"
#97200000000
0"
#97300000000
b1010111 $
1"
#97400000000
0"
#97500000000
b1011000 $
1"
#97600000000
0"
#97700000000
b1011001 $
1"
#97800000000
0"
#97900000000
b1011010 $
1"
#98000000000
0"
#98100000000
b1011011 $
1"
#98200000000
0"
#98300000000
b1011100 $
1"
#98400000000
0"
#98500000000
b1011101 $
1"
#98600000000
0"
#98700000000
b1011110 $
1"
#98800000000
0"
#98900000000
b1011111 $
1"
#99000000000
0"
#99100000000
b1100000 $
1"
#99200000000
0"
#99300000000
b1100001 $
1"
#99400000000
0"
#99500000000
b1100010 $
1"
#99600000000
0"
#99700000000
b1100011 $
1"
#99800000000
0"
#99900000000
b101 !
b101 %
b0 $
1"
#100000000000
0"
#100100000000
b1 $
1"
#100200000000
0"
#100300000000
b10 $
1"
#100400000000
0"
#100500000000
b11 $
1"
#100600000000
0"
#100700000000
b100 $
1"
#100800000000
0"
#100900000000
b101 $
1"
#101000000000
0"
#101100000000
b110 $
1"
#101200000000
0"
#101300000000
b111 $
1"
#101400000000
0"
#101500000000
b1000 $
1"
#101600000000
0"
#101700000000
b1001 $
1"
#101800000000
0"
#101900000000
b1010 $
1"
#102000000000
0"
#102100000000
b1011 $
1"
#102200000000
0"
#102300000000
b1100 $
1"
#102400000000
0"
#102500000000
b1101 $
1"
#102600000000
0"
#102700000000
b1110 $
1"
#102800000000
0"
#102900000000
b1111 $
1"
#103000000000
0"
#103100000000
b10000 $
1"
#103200000000
0"
#103300000000
b10001 $
1"
#103400000000
0"
#103500000000
b10010 $
1"
#103600000000
0"
#103700000000
b10011 $
1"
#103800000000
0"
#103900000000
b10100 $
1"
#104000000000
0"
#104100000000
b10101 $
1"
#104200000000
0"
#104300000000
b10110 $
1"
#104400000000
0"
#104500000000
b10111 $
1"
#104600000000
0"
#104700000000
b11000 $
1"
#104800000000
0"
#104900000000
b11001 $
1"
#105000000000
0"
#105100000000
b11010 $
1"
#105200000000
0"
#105300000000
b11011 $
1"
#105400000000
0"
#105500000000
b11100 $
1"
#105600000000
0"
#105700000000
b11101 $
1"
#105800000000
0"
#105900000000
b11110 $
1"
#106000000000
0"
#106100000000
b11111 $
1"
#106200000000
0"
#106300000000
b100000 $
1"
#106400000000
0"
#106500000000
b100001 $
1"
#106600000000
0"
#106700000000
b100010 $
1"
#106800000000
0"
#106900000000
b100011 $
1"
#107000000000
0"
#107100000000
b100100 $
1"
#107200000000
0"
#107300000000
b100101 $
1"
#107400000000
0"
#107500000000
b100110 $
1"
#107600000000
0"
#107700000000
b100111 $
1"
#107800000000
0"
#107900000000
b101000 $
1"
#108000000000
0"
#108100000000
b101001 $
1"
#108200000000
0"
#108300000000
b101010 $
1"
#108400000000
0"
#108500000000
b101011 $
1"
#108600000000
0"
#108700000000
b101100 $
1"
#108800000000
0"
#108900000000
b101101 $
1"
#109000000000
0"
#109100000000
b101110 $
1"
#109200000000
0"
#109300000000
b101111 $
1"
#109400000000
0"
#109500000000
b110000 $
1"
#109600000000
0"
#109700000000
b110001 $
1"
#109800000000
0"
#109900000000
b110010 $
1"
#110000000000
0"
#110100000000
b110011 $
1"
#110200000000
0"
#110300000000
b110100 $
1"
#110400000000
0"
#110500000000
b110101 $
1"
#110600000000
0"
#110700000000
b110110 $
1"
#110800000000
0"
#110900000000
b110111 $
1"
#111000000000
0"
#111100000000
b111000 $
1"
#111200000000
0"
#111300000000
b111001 $
1"
#111400000000
0"
#111500000000
b111010 $
1"
#111600000000
0"
#111700000000
b111011 $
1"
#111800000000
0"
#111900000000
b111100 $
1"
#112000000000
0"
#112100000000
b111101 $
1"
#112200000000
0"
#112300000000
b111110 $
1"
#112400000000
0"
#112500000000
b111111 $
1"
#112600000000
0"
#112700000000
b1000000 $
1"
#112800000000
0"
#112900000000
b1000001 $
1"
#113000000000
0"
#113100000000
b1000010 $
1"
#113200000000
0"
#113300000000
b1000011 $
1"
#113400000000
0"
#113500000000
b1000100 $
1"
#113600000000
0"
#113700000000
b1000101 $
1"
#113800000000
0"
#113900000000
b1000110 $
1"
#114000000000
0"
#114100000000
b1000111 $
1"
